dictenvy.py
dict_envy-0.2.0.dist-info/METADATA
dict_envy-0.2.0.dist-info/RECORD
dict_envy-0.2.0.dist-info/WHEEL
dict_envy-0.2.0.dist-info/top_level.txt
