Metadata-Version: 2.1
Name: dict-envy
Version: 0.2.0
Summary: dict-like grouping of environment variables
Home-page: http://github.com/madedotcom/dict-envy
Author: Roman Tomjak
Author-email: roman.tomjak@made.com
License: MIT
Platform: any
Classifier: Programming Language :: Python
Classifier: Development Status :: 3 - Alpha
Classifier: Natural Language :: English
Classifier: Environment :: Web Environment
Classifier: Intended Audience :: Developers
Classifier: License :: OSI Approved :: MIT License
Classifier: Operating System :: OS Independent
Classifier: Topic :: Software Development :: Libraries :: Python Modules
Classifier: Topic :: Software Development :: Libraries :: Application Frameworks
